gwx_core/__init__.py
gwx_core/services/__init__.py
gwx_core/services/abstract_serializer_service.py
gwx_core/utils/__init__.py
gwx_core/utils/extractor.py
gwx_core/utils/response.py
gwx_core/utils/stringify.py
tests/__init__.py
tests/utils_test_case.py
gwx_core-0.0.6.dist-info/LICENSE
gwx_core-0.0.6.dist-info/METADATA
gwx_core-0.0.6.dist-info/WHEEL
gwx_core-0.0.6.dist-info/top_level.txt
gwx_core-0.0.6.dist-info/RECORD
