Metadata-Version: 2.1
Name: gwx-core
Version: 0.0.6
Summary: Core libraries and modules for flask projects.
Home-page: https://bitbucket.org/groworxdigitalengineering/gwx-core/src/master/
Author: Jerric Calosor
Author-email: jerric.calosor@groworx.com.au
License: UNKNOWN
Platform: UNKNOWN
Classifier: Programming Language :: Python :: 3
Classifier: License :: OSI Approved :: MIT License
Classifier: Operating System :: OS Independent
Requires-Python: >=3.7
